{
  "version": "6",
  "dialect": "sqlite",
  "id": "c45b9b70-723f-4603-bc88-c2577d3d4c66",
  "prevId": "00000000-0000-0000-0000-000000000000",
  "tables": {
    "connections": {
      "name": "connections",
      "columns": {
        "id": {
          "name": "id",
          "type": "text",
          "primaryKey": true,
          "notNull": true,
          "autoincrement": false
        },
        "orgId": {
          "name": "orgId",
          "type": "text",
          "primaryKey": false,
          "notNull": true,
          "autoincrement": false
        },
        "label": {
          "name": "label",
          "type": "text",
          "primaryKey": false,
          "notNull": true,
          "autoincrement": false
        },
        "kind": {
          "name": "kind",
          "type": "text",
          "primaryKey": false,
          "notNull": true,
          "autoincrement": false
        },
        "namespace": {
          "name": "namespace",
          "type": "text",
          "primaryKey": false,
          "notNull": false,
          "autoincrement": false
        },
        "configJson": {
          "name": "configJson",
          "type": "text",
          "primaryKey": false,
          "notNull": true,
          "autoincrement": false
        },
        "updatedAt": {
          "name": "updatedAt",
          "type": "integer",
          "primaryKey": false,
          "notNull": false,
          "autoincrement": false,
          "default": "(cast((julianday('now') - 2440587.5)*86400000 as integer))"
        }
      },
      "indexes": {
        "connections_org_label_idx": {
          "name": "connections_org_label_idx",
          "columns": [
            "orgId",
            "label"
          ],
          "isUnique": true
        }
      },
      "foreignKeys": {
        "connections_orgId_orgs_id_fk": {
          "name": "connections_orgId_orgs_id_fk",
          "tableFrom": "connections",
          "tableTo": "orgs",
          "columnsFrom": [
            "orgId"
          ],
          "columnsTo": [
            "id"
          ],
          "onDelete": "cascade",
          "onUpdate": "no action"
        }
      },
      "compositePrimaryKeys": {},
      "uniqueConstraints": {},
      "checkConstraints": {}
    },
    "files": {
      "name": "files",
      "columns": {
        "id": {
          "name": "id",
          "type": "text",
          "primaryKey": true,
          "notNull": true,
          "autoincrement": false
        },
        "repoId": {
          "name": "repoId",
          "type": "text",
          "primaryKey": false,
          "notNull": true,
          "autoincrement": false
        },
        "path": {
          "name": "path",
          "type": "text",
          "primaryKey": false,
          "notNull": true,
          "autoincrement": false
        },
        "extension": {
          "name": "extension",
          "type": "text",
          "primaryKey": false,
          "notNull": true,
          "autoincrement": false
        },
        "title": {
          "name": "title",
          "type": "text",
          "primaryKey": false,
          "notNull": false,
          "autoincrement": false
        },
        "content": {
          "name": "content",
          "type": "text",
          "primaryKey": false,
          "notNull": true,
          "autoincrement": false
        },
        "updatedAt": {
          "name": "updatedAt",
          "type": "integer",
          "primaryKey": false,
          "notNull": false,
          "autoincrement": false,
          "default": "(cast((julianday('now') - 2440587.5)*86400000 as integer))"
        }
      },
      "indexes": {
        "files_repo_idx": {
          "name": "files_repo_idx",
          "columns": [
            "repoId"
          ],
          "isUnique": false
        },
        "files_repo_path_idx": {
          "name": "files_repo_path_idx",
          "columns": [
            "repoId",
            "path"
          ],
          "isUnique": true
        }
      },
      "foreignKeys": {
        "files_repoId_repos_id_fk": {
          "name": "files_repoId_repos_id_fk",
          "tableFrom": "files",
          "tableTo": "repos",
          "columnsFrom": [
            "repoId"
          ],
          "columnsTo": [
            "id"
          ],
          "onDelete": "cascade",
          "onUpdate": "no action"
        }
      },
      "compositePrimaryKeys": {},
      "uniqueConstraints": {},
      "checkConstraints": {}
    },
    "orgs": {
      "name": "orgs",
      "columns": {
        "id": {
          "name": "id",
          "type": "text",
          "primaryKey": true,
          "notNull": true,
          "autoincrement": false
        },
        "slug": {
          "name": "slug",
          "type": "text",
          "primaryKey": false,
          "notNull": true,
          "autoincrement": false
        },
        "name": {
          "name": "name",
          "type": "text",
          "primaryKey": false,
          "notNull": true,
          "autoincrement": false
        }
      },
      "indexes": {
        "orgs_slug_idx": {
          "name": "orgs_slug_idx",
          "columns": [
            "slug"
          ],
          "isUnique": true
        }
      },
      "foreignKeys": {},
      "compositePrimaryKeys": {},
      "uniqueConstraints": {},
      "checkConstraints": {}
    },
    "repos": {
      "name": "repos",
      "columns": {
        "id": {
          "name": "id",
          "type": "text",
          "primaryKey": true,
          "notNull": true,
          "autoincrement": false
        },
        "orgId": {
          "name": "orgId",
          "type": "text",
          "primaryKey": false,
          "notNull": true,
          "autoincrement": false
        },
        "slug": {
          "name": "slug",
          "type": "text",
          "primaryKey": false,
          "notNull": true,
          "autoincrement": false
        },
        "gitUrl": {
          "name": "gitUrl",
          "type": "text",
          "primaryKey": false,
          "notNull": false,
          "autoincrement": false
        },
        "isDefault": {
          "name": "isDefault",
          "type": "integer",
          "primaryKey": false,
          "notNull": true,
          "autoincrement": false,
          "default": false
        }
      },
      "indexes": {
        "repos_org_idx": {
          "name": "repos_org_idx",
          "columns": [
            "orgId"
          ],
          "isUnique": false
        },
        "repos_org_slug_idx": {
          "name": "repos_org_slug_idx",
          "columns": [
            "orgId",
            "slug"
          ],
          "isUnique": true
        }
      },
      "foreignKeys": {
        "repos_orgId_orgs_id_fk": {
          "name": "repos_orgId_orgs_id_fk",
          "tableFrom": "repos",
          "tableTo": "orgs",
          "columnsFrom": [
            "orgId"
          ],
          "columnsTo": [
            "id"
          ],
          "onDelete": "cascade",
          "onUpdate": "no action"
        }
      },
      "compositePrimaryKeys": {},
      "uniqueConstraints": {},
      "checkConstraints": {}
    },
    "users": {
      "name": "users",
      "columns": {
        "id": {
          "name": "id",
          "type": "text",
          "primaryKey": true,
          "notNull": true,
          "autoincrement": false
        },
        "email": {
          "name": "email",
          "type": "text",
          "primaryKey": false,
          "notNull": true,
          "autoincrement": false
        },
        "orgId": {
          "name": "orgId",
          "type": "text",
          "primaryKey": false,
          "notNull": true,
          "autoincrement": false
        },
        "role": {
          "name": "role",
          "type": "text",
          "primaryKey": false,
          "notNull": true,
          "autoincrement": false,
          "default": "'member'"
        }
      },
      "indexes": {
        "users_org_email_idx": {
          "name": "users_org_email_idx",
          "columns": [
            "orgId",
            "email"
          ],
          "isUnique": true
        }
      },
      "foreignKeys": {
        "users_orgId_orgs_id_fk": {
          "name": "users_orgId_orgs_id_fk",
          "tableFrom": "users",
          "tableTo": "orgs",
          "columnsFrom": [
            "orgId"
          ],
          "columnsTo": [
            "id"
          ],
          "onDelete": "cascade",
          "onUpdate": "no action"
        }
      },
      "compositePrimaryKeys": {},
      "uniqueConstraints": {},
      "checkConstraints": {}
    }
  },
  "views": {},
  "enums": {},
  "_meta": {
    "schemas": {},
    "tables": {},
    "columns": {}
  },
  "internal": {
    "indexes": {}
  }
}